lofargeotiff/__init__.py
lofargeotiff-0.1.dist-info/METADATA
lofargeotiff-0.1.dist-info/RECORD
lofargeotiff-0.1.dist-info/WHEEL
lofargeotiff-0.1.dist-info/top_level.txt
