Metadata-Version: 2.1
Name: lofargeotiff
Version: 0.1
Summary: Write LOFAR near field images as GeoTIFF
Home-page: https://github.com/tammojan/lofargeotiff
Author: Tammo Jan Dijkema
Author-email: dijkema@astron.nl
License: UNKNOWN
Platform: UNKNOWN
Classifier: Programming Language :: Python :: 3
Classifier: Programming Language :: Python :: 2
Classifier: License :: OSI Approved :: Apache Software License
Classifier: Operating System :: OS Independent
Requires-Python: >=2.7
Requires-Dist: lofarantpos
Requires-Dist: rasterio
